LICENSE
README.md
setup.py
edgetam_dimos.egg-info/PKG-INFO
edgetam_dimos.egg-info/SOURCES.txt
edgetam_dimos.egg-info/dependency_links.txt
edgetam_dimos.egg-info/requires.txt
edgetam_dimos.egg-info/top_level.txt
sam2/__init__.py
sam2/automatic_mask_generator.py
sam2/build_sam.py
sam2/sam2_image_predictor.py
sam2/sam2_video_predictor.py
sam2/modeling/__init__.py
sam2/modeling/memory_attention.py
sam2/modeling/memory_encoder.py
sam2/modeling/perceiver.py
sam2/modeling/position_encoding.py
sam2/modeling/sam2_base.py
sam2/modeling/sam2_utils.py
sam2/modeling/backbones/__init__.py
sam2/modeling/backbones/hieradet.py
sam2/modeling/backbones/image_encoder.py
sam2/modeling/backbones/timm.py
sam2/modeling/backbones/utils.py
sam2/modeling/sam/__init__.py
sam2/modeling/sam/mask_decoder.py
sam2/modeling/sam/prompt_encoder.py
sam2/modeling/sam/transformer.py
sam2/utils/__init__.py
sam2/utils/amg.py
sam2/utils/misc.py
sam2/utils/transforms.py