Metadata-Version: 2.4
Name: edgetam-dimos
Version: 1.0
Summary: EdgeTAM: On-Device Track Anything Model
Home-page: https://github.com/facebookresearch/EdgeTAM
Author: Meta AI
Author-email: chongzhou1024@gmail.com
License: Apache 2.0
Requires-Python: >=3.10.0
License-File: LICENSE
Requires-Dist: torch>=2.3.1
Requires-Dist: torchvision>=0.18.1
Requires-Dist: numpy>=1.24.4
Requires-Dist: tqdm>=4.66.1
Requires-Dist: hydra-core>=1.3.2
Requires-Dist: iopath>=0.1.10
Requires-Dist: pillow>=9.4.0
Provides-Extra: notebooks
Requires-Dist: matplotlib>=3.9.1; extra == "notebooks"
Requires-Dist: jupyter>=1.0.0; extra == "notebooks"
Requires-Dist: opencv-python>=4.7.0; extra == "notebooks"
Requires-Dist: eva-decord>=0.6.1; extra == "notebooks"
Provides-Extra: dev
Requires-Dist: black==24.2.0; extra == "dev"
Requires-Dist: usort==1.0.2; extra == "dev"
Requires-Dist: ufmt==2.0.0b2; extra == "dev"
Requires-Dist: fvcore>=0.1.5.post20221221; extra == "dev"
Requires-Dist: pandas>=2.2.2; extra == "dev"
Requires-Dist: scikit-image>=0.24.0; extra == "dev"
Requires-Dist: tensorboard>=2.17.0; extra == "dev"
Requires-Dist: pycocotools>=2.0.8; extra == "dev"
Requires-Dist: tensordict>=0.5.0; extra == "dev"
Requires-Dist: opencv-python>=4.7.0; extra == "dev"
Requires-Dist: submitit>=1.5.1; extra == "dev"
Provides-Extra: gradio
Requires-Dist: gradio==4.44.0; extra == "gradio"
Requires-Dist: gradio_client==1.3.0; extra == "gradio"
Requires-Dist: gradio_image_prompter==0.1.0; extra == "gradio"
Requires-Dist: opencv-python==4.10.0.84; extra == "gradio"
Requires-Dist: moviepy==1.0.3; extra == "gradio"
Requires-Dist: pydantic==2.10.6; extra == "gradio"
Requires-Dist: timm==1.0.15; extra == "gradio"
Requires-Dist: eva-decord==0.6.1; extra == "gradio"
Provides-Extra: coreml
Requires-Dist: coremltools>=8.0.0; extra == "coreml"
Requires-Dist: pillow>=9.4.0; extra == "coreml"
Requires-Dist: timm==1.0.15; extra == "coreml"
Dynamic: author
Dynamic: author-email
Dynamic: description
Dynamic: description-content-type
Dynamic: home-page
Dynamic: license
Dynamic: license-file
Dynamic: provides-extra
Dynamic: requires-dist
Dynamic: requires-python
Dynamic: summary
